too_easy/__init__.py
too_easy/py.typed
too_easy/version.py
too_easy-0.0.2.dist-info/LICENSE
too_easy-0.0.2.dist-info/METADATA
too_easy-0.0.2.dist-info/WHEEL
too_easy-0.0.2.dist-info/top_level.txt
too_easy-0.0.2.dist-info/RECORD
